cururo/__init__.py
cururo/cli.py
cururo/reviewer.py
cururo/lib/__init__.py
cururo/lib/ai_env.py
cururo/lib/env_modes.py
cururo/lib/openai_assistant.py
cururo/lib/web_publisher.py
cururo/util/__init__.py
cururo/util/handler.py
cururo/util/publisher.py
cururo/util/util.py
test/__init__.py
test/linter_test.py
test/test_openai_assistant.py
test/test_publisher.py
test/test_response_handler.py
test/test_response_processor.py
test/test_reviewer.py
test/lib/__init__.py
test/lib/test_env_modes.py
cururo-1.1.3.dist-info/LICENSE
cururo-1.1.3.dist-info/METADATA
cururo-1.1.3.dist-info/WHEEL
cururo-1.1.3.dist-info/entry_points.txt
cururo-1.1.3.dist-info/top_level.txt
cururo-1.1.3.dist-info/RECORD
