Metadata-Version: 2.1
Name: cururo
Version: 1.1.3
Summary: Review an item using OpenAI.
Author: Agustin Rios
Author-email: arios6@uc.cl
Classifier: Intended Audience :: Developers
Classifier: Programming Language :: Python :: 3
Classifier: Programming Language :: Python :: 3.6
Classifier: Programming Language :: Python :: 3.7
Classifier: Programming Language :: Python :: 3.8
Classifier: Programming Language :: Python :: 3.9
Classifier: Programming Language :: Python :: 3.10
Requires-Python: >=3.6
License-File: LICENSE
Requires-Dist: openai
Requires-Dist: PyGithub
Requires-Dist: requests
